minha_api_lib/__init__.py
minha_api_lib/cli.py
minha_api_lib/main.py
minha_api_lib/test_main.http
minha_api_lib/routers/__init__.py
minha_api_lib/routers/exemplo.py
minha_fastapi_lib-0.1.0.dist-info/METADATA
minha_fastapi_lib-0.1.0.dist-info/WHEEL
minha_fastapi_lib-0.1.0.dist-info/entry_points.txt
minha_fastapi_lib-0.1.0.dist-info/licenses/LICENSE
minha_fastapi_lib-0.1.0.dist-info/RECORD
